[{"numer-109": {"W PRODUKCJI": "The Cursed Crusade"}}, {"numer-109": {"W PRODUKCJI": "Men of War: Oddzia\u0142 Szturmowy"}}, {"numer-109": {"W PRODUKCJI": "The Dream Machine"}}, {"numer-109": {"W PRODUKCJI": "Tomb Raider"}}, {"numer-109": {"W PRODUKCJI": "Red Orchestra 2: Heroes of Stalingrad"}}, {"numer-109": {"W PRODUKCJI": "Jagged Alliance 2: Reloaded"}}, {"numer-109": {"W PRODUKCJI": "Knight's Contract"}}, {"numer-109": {"W PRODUKCJI": "Legends of Daemonica: Farepoynt?s Purgatory"}}, {"numer-109": {"W PRODUKCJI": "The Haunted: Hell?s Reach"}}, {"numer-109": {"W PRODUKCJI": "inFamous 2"}}, {"numer-109": {"W PRODUKCJI": "MotorStorm: Apocalypse"}}, {"numer-109": {"W PRODUKCJI": "Uncharted 3: Drake?s Deception"}}, {"numer-109": {"RECENZJE": "Killzone 3"}}, {"numer-109": {"RECENZJE": "Rajd Polski: Rally Poland"}}, {"numer-109": {"RECENZJE": "Battlefield: Bad Company 2 ? Vietnam"}}, {"numer-109": {"RECENZJE": "Back to the Future: It?s About Time"}}, {"numer-109": {"RECENZJE": "DeathSpank: Thongs of Virtue"}}, {"numer-109": {"RECENZJE": "Super Meat Boy"}}, {"numer-109": {"RECENZJE": "Poker Simulator"}}, {"numer-109": {"RECENZJE": "Art of Murder: Tajne Akta"}}, {"numer-109": {"RECENZJE": "Symulator Farmy 2011"}}, {"numer-109": {"RECENZJE": "Darkness Within 2: The Dark Lineage"}}, {"numer-109": {"RECENZJE": "Music Master Chopin: Rock"}}, {"numer-109": {"RECENZJE": "Ogniem i Mieczem: Dzikie Pola"}}, {"numer-109": {"RECENZJE": "Zapl\u0105tani"}}, {"numer-109": {"RECENZJE": "Crash Time IV: The Syndicate"}}, {"numer-109": {"RECENZJE": "Lionheart: Wyprawy Krzy\u017cowe"}}, {"numer-109": {"RECENZJE": "Pound of Ground"}}, {"numer-109": {"RECENZJE": "Maluch Racer 3"}}, {"numer-109": {"RECENZJE": "LittleBigPlanet 2"}}, {"numer-109": {"RECENZJE": "BlazBlue: Continuum Shift"}}, {"numer-109": {"RECENZJE": "Dead Nation"}}, {"numer-109": {"RECENZJE": "echochrome ii"}}, {"numer-109": {"RECENZJE": "Eat Them!"}}, {"numer-109": {"RECENZJE": "Tony Hawk: Shred"}}, {"numer-109": {"RECENZJE": "Reedycje:"}}, {"numer-109": {"RECENZJE": "Super Mario All-Stars"}}, {"numer-109": {"RECENZJE": "Prince of Persia: Trilogy"}}, {"numer-109": {"RECENZJE": "The Sly Collection"}}, {"numer-109": {"RECENZJE": "Gry na iOS:"}}, {"numer-109": {"RECENZJE": "Infinity Blade"}}, {"numer-109": {"RECENZJE": "Dungeon Hunter 2"}}, {"numer-109": {"RECENZJE": "Battlefield: Bad Company 2"}}, {"numer-109": {"RECENZJE": "Real Racing 2"}}, {"numer-109": {"RECENZJE": "Hero of Sparta II"}}, {"numer-109": {"RECENZJE": "Need for Speed Hot Pursuit"}}, {"numer-109": {"RECENZJE": "Shadow Guardian"}}, {"numer-109": {"RECENZJE": "Rage: Mutant Bash TV"}}, {"numer-109": {"RECENZJE": "Aralon: Sword and Shadow"}}, {"numer-109": {"RECENZJE": "Epic Mickey"}}]