[{"numer-125": {"RECENZJE": "Prototype 2"}}, {"numer-125": {"RECENZJE": "FIFA Street"}}, {"numer-125": {"RECENZJE": "Wargame: Zimna wojna"}}, {"numer-125": {"RECENZJE": "Vessel"}}, {"numer-125": {"RECENZJE": "Painkiller: Recurring Evil"}}, {"numer-125": {"RECENZJE": "Stacking"}}, {"numer-125": {"RECENZJE": "Street Fighter X Tekken"}}, {"numer-125": {"RECENZJE": "Deep Black: Reloaded"}}, {"numer-125": {"RECENZJE": "Da New Guys: Day Of The Jackass"}}, {"numer-125": {"RECENZJE": "Ninja Gaiden 3"}}, {"numer-125": {"RECENZJE": "Twisted Metal"}}, {"numer-125": {"RECENZJE": "Blades of Time"}}, {"numer-125": {"RECENZJE": "Warp"}}, {"numer-125": {"RECENZJE": "Microsoft Flight"}}, {"numer-125": {"RECENZJE": "Resident Evil: Operation Raccoon City"}}, {"numer-125": {"RECENZJE": "Silent Hill: Downpour"}}, {"numer-125": {"RECENZJE": "Yesterday"}}, {"numer-125": {"RECENZJE": "Death Road"}}]