[{"numer-165": {"W PRODUKCJI": "King's Quest"}}, {"numer-165": {"W PRODUKCJI": "Project Scissors: NightCry"}}, {"numer-165": {"W PRODUKCJI": "Wolfenstein: The Old Blood"}}, {"numer-165": {"W PRODUKCJI": "Acaratus"}}, {"numer-165": {"RECENZJE": "Pillars of Eternity"}}, {"numer-165": {"RECENZJE": "Zombie Army Trilogy"}}, {"numer-165": {"RECENZJE": "Hotline Miami 2: Wrong Number"}}, {"numer-165": {"RECENZJE": "Helldivers"}}, {"numer-165": {"RECENZJE": "Battlefield Hardline"}}, {"numer-165": {"RECENZJE": "Ori and the Blind Forest"}}, {"numer-165": {"RECENZJE": "ScreamRide"}}, {"numer-165": {"RECENZJE": "Worlds of Magic"}}, {"numer-165": {"RECENZJE": "Bloodborne"}}, {"numer-165": {"RECENZJE": "Sid Meier's Starships"}}, {"numer-165": {"RECENZJE": "Citizens of Earth"}}, {"numer-165": {"RECENZJE": "Obitus"}}, {"numer-165": {"RECENZJE": "Hand of Fate"}}, {"numer-165": {"RECENZJE": "A Druid's Duel"}}, {"numer-165": {"RECENZJE": "LA Cops"}}, {"numer-165": {"RECENZJE": "Cities: Skylines"}}, {"numer-165": {"RECENZJE": "White Night"}}, {"numer-165": {"RECENZJE": "The Deer God"}}, {"numer-165": {"RECENZJE": "Gravity Ghost"}}, {"numer-165": {"RECENZJE": "There Came an Echo"}}, {"numer-165": {"RECENZJE": "Ephemerid: A Musical Adventure"}}, {"numer-165": {"RECENZJE": "Tormentum: Dark Sorrow"}}, {"numer-165": {"RECENZJE": "Woolfe - The Red Hood Diaries"}}, {"numer-165": {"RECENZJE": "Assassin's Creed: Rogue PC"}}, {"numer-165": {"RECENZJE": "Monster Hunter 4 Ultimate"}}, {"numer-165": {"RECENZJE": "Shelter 2"}}, {"numer-165": {"RECENZJE": "Final Fantasy Type-0 HD"}}, {"numer-165": {"RECENZJE": "DmC Devil May Cry: Definitive Edition"}}, {"numer-165": {"RECENZJE": "Call of Duty: Advanced Warfare - Havoc DLC"}}, {"numer-165": {"RECENZJE": "Lords of the Fallen: Prastary labirynt DLC"}}, {"numer-165": {"JU\u017b GRALI\u015aMY": "Mad Max"}}, {"numer-165": {"JU\u017b GRALI\u015aMY": "Might & Magic: Heroes VII"}}, {"numer-165": {"JU\u017b GRALI\u015aMY": "Final Fantasy XV"}}, {"numer-165": {"JU\u017b GRALI\u015aMY": "Unreal Tournament"}}, {"numer-165": {"JU\u017b GRALI\u015aMY": "Supernova"}}, {"numer-165": {"JU\u017b GRALI\u015aMY": "Skyforge"}}, {"numer-165": {"JU\u017b GRALI\u015aMY": "Medieval Engineers"}}, {"numer-165": {"JU\u017b GRALI\u015aMY": "Hardland"}}, {"numer-165": {"JU\u017b GRALI\u015aMY": "Warlocks vs. Shadows"}}, {"numer-165": {"JU\u017b GRALI\u015aMY": "Darkwood"}}, {"numer-165": {"JU\u017b GRALI\u015aMY": "World of Tanks: Generals"}}, {"numer-165": {"JU\u017b GRALI\u015aMY": "Victor Vran"}}, {"numer-165": {"JU\u017b GRALI\u015aMY": "Eden Star"}}, {"numer-165": {"JU\u017b GRALI\u015aMY": "Offworld Trading Company"}}, {"numer-165": {"JU\u017b GRALI\u015aMY": "Duelyst"}}]