[{"105 pa\u017adziernik 2010": {"W PRODUKCJI": "DiRT 3"}}, {"105 pa\u017adziernik 2010": {"W PRODUKCJI": "Alice: Madness Returns"}}, {"105 pa\u017adziernik 2010": {"W PRODUKCJI": "Warhammer 40,000: Dark Millenium Online"}}, {"105 pa\u017adziernik 2010": {"W PRODUKCJI": "El Shaddai: Ascension of the Metatron"}}, {"105 pa\u017adziernik 2010": {"W PRODUKCJI": "Splatterhouse"}}, {"105 pa\u017adziernik 2010": {"W PRODUKCJI": "FireFall"}}, {"105 pa\u017adziernik 2010": {"W PRODUKCJI": "Call of Duty: Black Ops (betatest)"}}, {"105 pa\u017adziernik 2010": {"W PRODUKCJI": "Two Worlds II (betatest)"}}, {"105 pa\u017adziernik 2010": {"W PRODUKCJI": "Company of Heroes Online (betatest)"}}, {"105 pa\u017adziernik 2010": {"W PRODUKCJI": "Need for Speed Hot Pursuit (betatest)"}}, {"105 pa\u017adziernik 2010": {"W PRODUKCJI": "Lego Universe (betatest)"}}, {"105 pa\u017adziernik 2010": {"RECENZJE": "FIFA 11"}}, {"105 pa\u017adziernik 2010": {"RECENZJE": "King?s Bounty: Nowe \u015awiaty"}}, {"105 pa\u017adziernik 2010": {"RECENZJE": "Amnesia: The Dark Descent"}}, {"105 pa\u017adziernik 2010": {"RECENZJE": "Darksiders"}}, {"105 pa\u017adziernik 2010": {"RECENZJE": "Clone Wars Adventures"}}, {"105 pa\u017adziernik 2010": {"RECENZJE": "RUSE"}}, {"105 pa\u017adziernik 2010": {"RECENZJE": "Puzzle Quest 2"}}, {"105 pa\u017adziernik 2010": {"RECENZJE": "Tom Clancy?s HAWX 2"}}, {"105 pa\u017adziernik 2010": {"RECENZJE": "Civilization V"}}, {"105 pa\u017adziernik 2010": {"RECENZJE": "BlazBlue: Calamity Trigger"}}, {"105 pa\u017adziernik 2010": {"RECENZJE": "Guild 2: Renaissance"}}, {"105 pa\u017adziernik 2010": {"RECENZJE": "Alter Ego"}}, {"105 pa\u017adziernik 2010": {"RECENZJE": "The Lost Crown: A Ghost-Hunting Adventure"}}, {"105 pa\u017adziernik 2010": {"RECENZJE": "House M.D."}}, {"105 pa\u017adziernik 2010": {"RECENZJE": "Sam & Max Season 3: The Devil?s Playhouse"}}, {"105 pa\u017adziernik 2010": {"RECENZJE": "Burn Zombie Burn"}}, {"105 pa\u017adziernik 2010": {"RECENZJE": "F1 2010"}}, {"105 pa\u017adziernik 2010": {"RECENZJE": "Halo: Reach"}}, {"105 pa\u017adziernik 2010": {"RECENZJE": "Spider-Man: Shattered Dimensions"}}, {"105 pa\u017adziernik 2010": {"RECENZJE": "NHL 11"}}, {"105 pa\u017adziernik 2010": {"RECENZJE": "Guitar Hero: Warriors of Rock"}}, {"105 pa\u017adziernik 2010": {"RECENZJE": "Enslaved: Odyssey to the West"}}, {"105 pa\u017adziernik 2010": {"RECENZJE": "Sports Champions"}}, {"105 pa\u017adziernik 2010": {"RECENZJE": "Kung Fu Rider"}}, {"105 pa\u017adziernik 2010": {"RECENZJE": "Start the Party!"}}]