[{"numer-6": {"RECENZJE": "Freelancer"}}, {"numer-6": {"RECENZJE": "Praetorians"}}, {"numer-6": {"RECENZJE": "Hot Wheels: Bash Arena"}}, {"numer-6": {"RECENZJE": "I Was an Atomic Mutant"}}, {"numer-6": {"RECENZJE": "Splinter Cell"}}, {"numer-6": {"RECENZJE": "Gothic 2"}}, {"numer-6": {"RECENZJE": "Nascar 2003"}}, {"numer-6": {"RECENZJE": "Metal Gear Solid 2: Substance"}}, {"numer-6": {"RECENZJE": "Battlefield 1942: The Road to Rome"}}, {"numer-6": {"RECENZJE": "HoverAce"}}, {"numer-6": {"RECENZJE": "Project IGI 2"}}, {"numer-6": {"RECENZJE": "American Conquest"}}, {"numer-6": {"RECENZJE": "R6: Raven Shield"}}, {"numer-6": {"RECENZJE": "Realm of Hepumia"}}, {"numer-6": {"RECENZJE": "World of Outlaws Sprint Cars"}}, {"numer-6": {"RECENZJE": "Trailer Park Tycoon"}}, {"numer-6": {"RECENZJE": "Dirt Track Racing 2"}}, {"numer-6": {"RECENZJE": "Szymek Czarodziej PL"}}, {"numer-6": {"RECENZJE": "II Wojna \u015awiatowa PL"}}, {"numer-6": {"RECENZJE": "Celtic Kings PL"}}, {"numer-6": {"RECENZJE": "Master of Orion 3 PL"}}]