[{"117 wrzesie\u0144 2011": {"W PRODUKCJI": "Borderlands 2"}}, {"117 wrzesie\u0144 2011": {"W PRODUKCJI": "Dishonored"}}, {"117 wrzesie\u0144 2011": {"W PRODUKCJI": "Armored Core V"}}, {"117 wrzesie\u0144 2011": {"W PRODUKCJI": "Rage"}}, {"117 wrzesie\u0144 2011": {"W PRODUKCJI": "Dark Souls"}}, {"117 wrzesie\u0144 2011": {"W PRODUKCJI": "Binary Domain"}}, {"117 wrzesie\u0144 2011": {"W PRODUKCJI": "Battlefield 3"}}, {"117 wrzesie\u0144 2011": {"W PRODUKCJI": "W\u0142adca Pier\u015bcieni: Wojna na P\u00f3\u0142nocy"}}, {"117 wrzesie\u0144 2011": {"W PRODUKCJI": "FIFA Street"}}, {"117 wrzesie\u0144 2011": {"W PRODUKCJI": "NBA 2K12"}}, {"117 wrzesie\u0144 2011": {"W PRODUKCJI": "WildStar"}}, {"117 wrzesie\u0144 2011": {"W PRODUKCJI": "Ridge Racer Unbounded"}}, {"117 wrzesie\u0144 2011": {"W PRODUKCJI": "Dust 514"}}, {"117 wrzesie\u0144 2011": {"W PRODUKCJI": "Guild Wars 2"}}, {"117 wrzesie\u0144 2011": {"W PRODUKCJI": "Call of Duty: Modern Warfare 3"}}, {"117 wrzesie\u0144 2011": {"W PRODUKCJI": "Dragon?s Dogma"}}, {"117 wrzesie\u0144 2011": {"W PRODUKCJI": "Secret Files 3"}}, {"117 wrzesie\u0144 2011": {"W PRODUKCJI": "King Arthur II"}}, {"117 wrzesie\u0144 2011": {"W PRODUKCJI": "Dragon Commander"}}, {"117 wrzesie\u0144 2011": {"W PRODUKCJI": "The Adventures of Tintin: The Secret of the Unicorn"}}, {"117 wrzesie\u0144 2011": {"W PRODUKCJI": "SSX"}}, {"117 wrzesie\u0144 2011": {"W PRODUKCJI": "Assassin?s Creed Revelations"}}, {"117 wrzesie\u0144 2011": {"W PRODUKCJI": "Batman: Arkham City"}}, {"117 wrzesie\u0144 2011": {"W PRODUKCJI": "World of Warplanes"}}, {"117 wrzesie\u0144 2011": {"W PRODUKCJI": "Lollipop Chainsaw"}}, {"117 wrzesie\u0144 2011": {"W PRODUKCJI": "Ace Combat: Assault Horizon"}}, {"117 wrzesie\u0144 2011": {"W PRODUKCJI": "Kingdoms of Amalur: Reckoning"}}, {"117 wrzesie\u0144 2011": {"W PRODUKCJI": "Prototype 2"}}, {"117 wrzesie\u0144 2011": {"W PRODUKCJI": "Warhammer Online: Wrath of Heroes"}}, {"117 wrzesie\u0144 2011": {"W PRODUKCJI": "Wied\u017amin 2 v2.0"}}, {"117 wrzesie\u0144 2011": {"W PRODUKCJI": "Smite"}}, {"117 wrzesie\u0144 2011": {"W PRODUKCJI": "Need for Speed The Run"}}, {"117 wrzesie\u0144 2011": {"W PRODUKCJI": "Star Wars: The Old Republic"}}, {"117 wrzesie\u0144 2011": {"W PRODUKCJI": "Magna Mundi"}}, {"117 wrzesie\u0144 2011": {"W PRODUKCJI": "God of War Collection Volume II"}}, {"117 wrzesie\u0144 2011": {"W PRODUKCJI": "Metal Gear Solid HD Collection"}}, {"117 wrzesie\u0144 2011": {"W PRODUKCJI": "Silent Hill HD Collection"}}, {"117 wrzesie\u0144 2011": {"W PRODUKCJI": "Resident Evil: Revival Collection"}}, {"117 wrzesie\u0144 2011": {"W PRODUKCJI": "Ico & Shadow of the Collossus HD"}}, {"117 wrzesie\u0144 2011": {"W PRODUKCJI": "Halo: Combat Evolved Anniversary"}}, {"117 wrzesie\u0144 2011": {"W PRODUKCJI": "Diablo III"}}, {"117 wrzesie\u0144 2011": {"W PRODUKCJI": "Gears of War 3"}}, {"117 wrzesie\u0144 2011": {"W PRODUKCJI": "League of Legends: Dominion"}}, {"117 wrzesie\u0144 2011": {"W PRODUKCJI": "Anno 2070"}}, {"117 wrzesie\u0144 2011": {"W PRODUKCJI": "Hard Reset"}}, {"117 wrzesie\u0144 2011": {"RECENZJE": "Deus Ex: Human Revolution ? Bunt Ludzko\u015bci"}}, {"117 wrzesie\u0144 2011": {"RECENZJE": "Driver San Francisco"}}, {"117 wrzesie\u0144 2011": {"RECENZJE": "Dragon Age II: Dziedzictwo"}}, {"117 wrzesie\u0144 2011": {"RECENZJE": "Gods & Heroes: Rome Rising"}}, {"117 wrzesie\u0144 2011": {"RECENZJE": "Trauma"}}, {"117 wrzesie\u0144 2011": {"RECENZJE": "Limbo (PC)"}}, {"117 wrzesie\u0144 2011": {"RECENZJE": "E.Y.E: Divine Cybermancy"}}, {"117 wrzesie\u0144 2011": {"RECENZJE": "Patrician IV: Narodziny Dynastii"}}, {"117 wrzesie\u0144 2011": {"RECENZJE": "Vampire Saga: Welcome to Hell Lock"}}, {"117 wrzesie\u0144 2011": {"RECENZJE": "Dead Horde"}}, {"117 wrzesie\u0144 2011": {"RECENZJE": "Bastion"}}, {"117 wrzesie\u0144 2011": {"RECENZJE": "Insanely Twisted Shadow Planet"}}, {"117 wrzesie\u0144 2011": {"RECENZJE": "Toy Soldiers: Cold War"}}, {"117 wrzesie\u0144 2011": {"RECENZJE": "Ms. Splosion Man"}}, {"117 wrzesie\u0144 2011": {"RECENZJE": "Final Fantasy Tactics: The War of the Lions"}}, {"117 wrzesie\u0144 2011": {"RECENZJE": "Shift 2 Unleashed (mobile)"}}]